[
  "{\n    \"address\": \"11097 S Willow Walk Dr, South Jordan, UT 84009\",\n    \"date_sold\": \"Dec 27, 2022\"\n}",
  "{\n    \"address\": \"761 W Blue Magic Ln Unit 203, Midvale, UT 84047\",\n    \"date_sold\": \"Dec 27, 2022\"\n}",
  "{\n    \"address\": \"12077 E Milona Dr, Draper, UT 84020\",\n    \"date_sold\": \"Dec 22, 2022\"\n}",
  "{\n    \"address\": \"3524 S Blair Cir, South Salt Lake, UT 84115\",\n    \"date_sold\": \"Dec 20, 2022\"\n}",
  "{\n    \"address\": \"1745 W 400 N, Salt Lake City, UT 84116\",\n    \"date_sold\": \"Dec 19, 2022\"\n}",
  "{\n    \"address\": \"7606 S New Sycamore Dr # 170, West Jordan, UT 84081\",\n    \"date_sold\": \"Dec 18, 2022\"\n}",
  "{\n    \"address\": \"7608 S New Sycamore Dr # 169, West Jordan, UT 84081\",\n    \"date_sold\": \"Dec 18, 2022\"\n}",
  "{\n    \"address\": \"7602 S New Sycamore Dr # 172, West Jordan, UT 84081\",\n    \"date_sold\": \"Dec 18, 2022\"\n}",
  "{\n    \"address\": \"6043 W Sparrow View Dr, South Jordan, UT 84009\",\n    \"date_sold\": \"Dec 18, 2022\"\n}",
  "{\n    \"address\": \"7622 S New Sycamore Dr # 176, West Jordan, UT 84081\",\n    \"date_sold\": \"Dec 17, 2022\"\n}",
  "{\n    \"address\": \"1221 W Tamarack Rd, Taylorsville, UT 84123\",\n    \"date_sold\": \"Dec 17, 2022\"\n}",
  "{\n    \"address\": \"5094 S Lambeth St, Taylorsville, UT 84129\",\n    \"date_sold\": \"Dec 15, 2022\"\n}",
  "{\n    \"address\": \"6022 W Folly Island Way # 327, South Jordan, UT 84009\",\n    \"date_sold\": \"Dec 15, 2022\"\n}",
  "{\n    \"address\": \"13271 S Sky Ranch Rd, Herriman, UT 84096\",\n    \"date_sold\": \"Dec 15, 2022\"\n}",
  "{\n    \"address\": \"1469 W California Ave, Salt Lake City, UT 84104\",\n    \"date_sold\": \"Dec 14, 2022\"\n}",
  "{\n    \"address\": \"903 E Lafayette St, Sandy, UT 84094\",\n    \"date_sold\": \"Dec 14, 2022\"\n}",
  "{\n    \"address\": \"5909 W Feldspar Way, West Jordan, UT 84081\",\n    \"date_sold\": \"Dec 14, 2022\"\n}",
  "{\n    \"address\": \"9816 S Kramer Dr, Sandy, UT 84092\",\n    \"date_sold\": \"Dec 14, 2022\"\n}",
  "{\n    \"address\": \"5055 W 3000 S, West Valley City, UT 84120\",\n    \"date_sold\": \"Dec 13, 2022\"\n}",
  "{\n    \"address\": \"6642 W Skip Rock Rd # 433, South Jordan, UT 84009\",\n    \"date_sold\": \"Dec 13, 2022\"\n}",
  "{\n    \"address\": \"3743 W Lilac Heights Dr, South Jordan, UT 84095\",\n    \"date_sold\": \"Dec 13, 2022\"\n}",
  "{\n    \"address\": \"2851 W Teamsters Dr, South Jordan, UT 84095\",\n    \"date_sold\": \"Dec 13, 2022\"\n}",
  "{\n    \"address\": \"10224 S Willamette Way, South Jordan, UT 84009\",\n    \"date_sold\": \"Dec 13, 2022\"\n}",
  "{\n    \"address\": \"650 E 4025 S Unit C, Salt Lake City, UT 84107\",\n    \"date_sold\": \"Dec 13, 2022\"\n}",
  "{\n    \"address\": \"824 E 3950 S Apt C, Salt Lake City, UT 84107\",\n    \"date_sold\": \"Dec 12, 2022\"\n}",
  "{\n    \"address\": \"6475 S 1655 E, Salt Lake City, UT 84121\",\n    \"date_sold\": \"Dec 12, 2022\"\n}",
  "{\n    \"address\": \"2417 W Rustic Roads Dr, South Jordan, UT 84095\",\n    \"date_sold\": \"Dec 12, 2022\"\n}",
  "{\n    \"address\": \"4788 W Harbor St, West Valley City, UT 84120\",\n    \"date_sold\": \"Dec 12, 2022\"\n}",
  "{\n    \"address\": \"2476 E Cardinal Way, Salt Lake City, UT 84121\",\n    \"date_sold\": \"Dec 12, 2022\"\n}",
  "{\n    \"address\": \"5109 W 5320 S, Salt Lake City, UT 84118\",\n    \"date_sold\": \"Dec 12, 2022\"\n}",
  "{\n    \"address\": \"15023 S Pastoral Way, Bluffdale, UT 84065\",\n    \"date_sold\": \"Dec 12, 2022\"\n}",
  "{\n    \"address\": \"2220 E Murray Holladay Rd Apt 160, Salt Lake City, UT 84117\",\n    \"date_sold\": \"Dec 12, 2022\"\n}",
  "{\n    \"address\": \"181 E 5460 S Apt 1, Salt Lake City, UT 84107\",\n    \"date_sold\": \"Dec 12, 2022\"\n}",
  "{\n    \"address\": \"4931 W 6400 S, West Jordan, UT 84081\",\n    \"date_sold\": \"Dec 12, 2022\"\n}",
  "{\n    \"address\": \"310 E Carole Cir, Salt Lake City, UT 84115\",\n    \"date_sold\": \"Dec 12, 2022\"\n}",
  "{\n    \"address\": \"8969 S Flatiron Dr, Sandy, UT 84093\",\n    \"date_sold\": \"Dec 12, 2022\"\n}",
  "{\n    \"address\": \"1549 E Waterbury Dr Unit L, Salt Lake City, UT 84121\",\n    \"date_sold\": \"Dec 12, 2022\"\n}",
  "{\n    \"address\": \"116 E Resaca Dr Unit F2, Sandy, UT 84070\",\n    \"date_sold\": \"Dec 11, 2022\"\n}",
  "{\n    \"address\": \"2191 E Mabey Dr, Salt Lake City, UT 84109\",\n    \"date_sold\": \"Dec 10, 2022\"\n}",
  "{\n    \"address\": \"10822 S Wynview Ln, South Jordan, UT 84095\",\n    \"date_sold\": \"Dec 10, 2022\"\n}",
  "{\n    \"address\": \"11632 S Scare Crow Ct, South Jordan, UT 84009\",\n    \"date_sold\": \"Dec 10, 2022\"\n}",
  "{\n    \"address\": \"3897 W Fawn Hill Ln, Bluffdale, UT 84065\",\n    \"date_sold\": \"Dec 10, 2022\"\n}",
  "{\n    \"address\": \"11097 S Willow Walk Dr, South Jordan, UT 84009\",\n    \"date_sold\": \"Dec 27, 2022\"\n}",
  "{\n    \"address\": \"761 W Blue Magic Ln Unit 203, Midvale, UT 84047\",\n    \"date_sold\": \"Dec 27, 2022\"\n}",
  "{\n    \"address\": \"12077 E Milona Dr, Draper, UT 84020\",\n    \"date_sold\": \"Dec 22, 2022\"\n}",
  "{\n    \"address\": \"3524 S Blair Cir, South Salt Lake, UT 84115\",\n    \"date_sold\": \"Dec 20, 2022\"\n}",
  "{\n    \"address\": \"1745 W 400 N, Salt Lake City, UT 84116\",\n    \"date_sold\": \"Dec 19, 2022\"\n}",
  "{\n    \"address\": \"7606 S New Sycamore Dr # 170, West Jordan, UT 84081\",\n    \"date_sold\": \"Dec 18, 2022\"\n}",
  "{\n    \"address\": \"7608 S New Sycamore Dr # 169, West Jordan, UT 84081\",\n    \"date_sold\": \"Dec 18, 2022\"\n}",
  "{\n    \"address\": \"7602 S New Sycamore Dr # 172, West Jordan, UT 84081\",\n    \"date_sold\": \"Dec 18, 2022\"\n}",
  "{\n    \"address\": \"6043 W Sparrow View Dr, South Jordan, UT 84009\",\n    \"date_sold\": \"Dec 18, 2022\"\n}",
  "{\n    \"address\": \"7622 S New Sycamore Dr # 176, West Jordan, UT 84081\",\n    \"date_sold\": \"Dec 17, 2022\"\n}",
  "{\n    \"address\": \"1221 W Tamarack Rd, Taylorsville, UT 84123\",\n    \"date_sold\": \"Dec 17, 2022\"\n}",
  "{\n    \"address\": \"5094 S Lambeth St, Taylorsville, UT 84129\",\n    \"date_sold\": \"Dec 15, 2022\"\n}",
  "{\n    \"address\": \"13271 S Sky Ranch Rd, Herriman, UT 84096\",\n    \"date_sold\": \"Dec 15, 2022\"\n}",
  "{\n    \"address\": \"6022 W Folly Island Way # 327, South Jordan, UT 84009\",\n    \"date_sold\": \"Dec 15, 2022\"\n}",
  "{\n    \"address\": \"1469 W California Ave, Salt Lake City, UT 84104\",\n    \"date_sold\": \"Dec 14, 2022\"\n}",
  "{\n    \"address\": \"903 E Lafayette St, Sandy, UT 84094\",\n    \"date_sold\": \"Dec 14, 2022\"\n}",
  "{\n    \"address\": \"5909 W Feldspar Way, West Jordan, UT 84081\",\n    \"date_sold\": \"Dec 14, 2022\"\n}",
  "{\n    \"address\": \"9816 S Kramer Dr, Sandy, UT 84092\",\n    \"date_sold\": \"Dec 14, 2022\"\n}",
  "{\n    \"address\": \"5055 W 3000 S, West Valley City, UT 84120\",\n    \"date_sold\": \"Dec 13, 2022\"\n}",
  "{\n    \"address\": \"6642 W Skip Rock Rd # 433, South Jordan, UT 84009\",\n    \"date_sold\": \"Dec 13, 2022\"\n}",
  "{\n    \"address\": \"3743 W Lilac Heights Dr, South Jordan, UT 84095\",\n    \"date_sold\": \"Dec 13, 2022\"\n}",
  "{\n    \"address\": \"2851 W Teamsters Dr, South Jordan, UT 84095\",\n    \"date_sold\": \"Dec 13, 2022\"\n}",
  "{\n    \"address\": \"10224 S Willamette Way, South Jordan, UT 84009\",\n    \"date_sold\": \"Dec 13, 2022\"\n}",
  "{\n    \"address\": \"650 E 4025 S Unit C, Salt Lake City, UT 84107\",\n    \"date_sold\": \"Dec 13, 2022\"\n}",
  "{\n    \"address\": \"824 E 3950 S Apt C, Salt Lake City, UT 84107\",\n    \"date_sold\": \"Dec 12, 2022\"\n}",
  "{\n    \"address\": \"6475 S 1655 E, Salt Lake City, UT 84121\",\n    \"date_sold\": \"Dec 12, 2022\"\n}",
  "{\n    \"address\": \"2417 W Rustic Roads Dr, South Jordan, UT 84095\",\n    \"date_sold\": \"Dec 12, 2022\"\n}",
  "{\n    \"address\": \"4788 W Harbor St, West Valley City, UT 84120\",\n    \"date_sold\": \"Dec 12, 2022\"\n}",
  "{\n    \"address\": \"2476 E Cardinal Way, Salt Lake City, UT 84121\",\n    \"date_sold\": \"Dec 12, 2022\"\n}",
  "{\n    \"address\": \"2220 E Murray Holladay Rd Apt 160, Salt Lake City, UT 84117\",\n    \"date_sold\": \"Dec 12, 2022\"\n}",
  "{\n    \"address\": \"15023 S Pastoral Way, Bluffdale, UT 84065\",\n    \"date_sold\": \"Dec 12, 2022\"\n}",
  "{\n    \"address\": \"5109 W 5320 S, Salt Lake City, UT 84118\",\n    \"date_sold\": \"Dec 12, 2022\"\n}",
  "{\n    \"address\": \"181 E 5460 S Apt 1, Salt Lake City, UT 84107\",\n    \"date_sold\": \"Dec 12, 2022\"\n}",
  "{\n    \"address\": \"4931 W 6400 S, West Jordan, UT 84081\",\n    \"date_sold\": \"Dec 12, 2022\"\n}",
  "{\n    \"address\": \"310 E Carole Cir, Salt Lake City, UT 84115\",\n    \"date_sold\": \"Dec 12, 2022\"\n}",
  "{\n    \"address\": \"1549 E Waterbury Dr Unit L, Salt Lake City, UT 84121\",\n    \"date_sold\": \"Dec 12, 2022\"\n}",
  "{\n    \"address\": \"8969 S Flatiron Dr, Sandy, UT 84093\",\n    \"date_sold\": \"Dec 12, 2022\"\n}",
  "{\n    \"address\": \"116 E Resaca Dr Unit F2, Sandy, UT 84070\",\n    \"date_sold\": \"Dec 11, 2022\"\n}",
  "{\n    \"address\": \"10822 S Wynview Ln, South Jordan, UT 84095\",\n    \"date_sold\": \"Dec 10, 2022\"\n}",
  "{\n    \"address\": \"2191 E Mabey Dr, Salt Lake City, UT 84109\",\n    \"date_sold\": \"Dec 10, 2022\"\n}",
  "{\n    \"address\": \"11632 S Scare Crow Ct, South Jordan, UT 84009\",\n    \"date_sold\": \"Dec 10, 2022\"\n}",
  "{\n    \"address\": \"3897 W Fawn Hill Ln, Bluffdale, UT 84065\",\n    \"date_sold\": \"Dec 10, 2022\"\n}",
  "{\n    \"address\": \"11097 S Willow Walk Dr, South Jordan, UT 84009\",\n    \"date_sold\": \"Dec 27, 2022\"\n}",
  "{\n    \"address\": \"761 W Blue Magic Ln Unit 203, Midvale, UT 84047\",\n    \"date_sold\": \"Dec 27, 2022\"\n}",
  "{\n    \"address\": \"12077 E Milona Dr, Draper, UT 84020\",\n    \"date_sold\": \"Dec 22, 2022\"\n}",
  "{\n    \"address\": \"3524 S Blair Cir, South Salt Lake, UT 84115\",\n    \"date_sold\": \"Dec 20, 2022\"\n}",
  "{\n    \"address\": \"1745 W 400 N, Salt Lake City, UT 84116\",\n    \"date_sold\": \"Dec 19, 2022\"\n}",
  "{\n    \"address\": \"7606 S New Sycamore Dr # 170, West Jordan, UT 84081\",\n    \"date_sold\": \"Dec 18, 2022\"\n}",
  "{\n    \"address\": \"7608 S New Sycamore Dr # 169, West Jordan, UT 84081\",\n    \"date_sold\": \"Dec 18, 2022\"\n}",
  "{\n    \"address\": \"7602 S New Sycamore Dr # 172, West Jordan, UT 84081\",\n    \"date_sold\": \"Dec 18, 2022\"\n}",
  "{\n    \"address\": \"6043 W Sparrow View Dr, South Jordan, UT 84009\",\n    \"date_sold\": \"Dec 18, 2022\"\n}",
  "{\n    \"address\": \"7622 S New Sycamore Dr # 176, West Jordan, UT 84081\",\n    \"date_sold\": \"Dec 17, 2022\"\n}",
  "{\n    \"address\": \"1221 W Tamarack Rd, Taylorsville, UT 84123\",\n    \"date_sold\": \"Dec 17, 2022\"\n}",
  "{\n    \"address\": \"5094 S Lambeth St, Taylorsville, UT 84129\",\n    \"date_sold\": \"Dec 15, 2022\"\n}",
  "{\n    \"address\": \"13271 S Sky Ranch Rd, Herriman, UT 84096\",\n    \"date_sold\": \"Dec 15, 2022\"\n}",
  "{\n    \"address\": \"6022 W Folly Island Way # 327, South Jordan, UT 84009\",\n    \"date_sold\": \"Dec 15, 2022\"\n}",
  "{\n    \"address\": \"903 E Lafayette St, Sandy, UT 84094\",\n    \"date_sold\": \"Dec 14, 2022\"\n}",
  "{\n    \"address\": \"1469 W California Ave, Salt Lake City, UT 84104\",\n    \"date_sold\": \"Dec 14, 2022\"\n}",
  "{\n    \"address\": \"5909 W Feldspar Way, West Jordan, UT 84081\",\n    \"date_sold\": \"Dec 14, 2022\"\n}",
  "{\n    \"address\": \"9816 S Kramer Dr, Sandy, UT 84092\",\n    \"date_sold\": \"Dec 14, 2022\"\n}",
  "{\n    \"address\": \"5055 W 3000 S, West Valley City, UT 84120\",\n    \"date_sold\": \"Dec 13, 2022\"\n}",
  "{\n    \"address\": \"6642 W Skip Rock Rd # 433, South Jordan, UT 84009\",\n    \"date_sold\": \"Dec 13, 2022\"\n}",
  "{\n    \"address\": \"3743 W Lilac Heights Dr, South Jordan, UT 84095\",\n    \"date_sold\": \"Dec 13, 2022\"\n}",
  "{\n    \"address\": \"2851 W Teamsters Dr, South Jordan, UT 84095\",\n    \"date_sold\": \"Dec 13, 2022\"\n}",
  "{\n    \"address\": \"10224 S Willamette Way, South Jordan, UT 84009\",\n    \"date_sold\": \"Dec 13, 2022\"\n}",
  "{\n    \"address\": \"650 E 4025 S Unit C, Salt Lake City, UT 84107\",\n    \"date_sold\": \"Dec 13, 2022\"\n}",
  "{\n    \"address\": \"824 E 3950 S Apt C, Salt Lake City, UT 84107\",\n    \"date_sold\": \"Dec 12, 2022\"\n}",
  "{\n    \"address\": \"2417 W Rustic Roads Dr, South Jordan, UT 84095\",\n    \"date_sold\": \"Dec 12, 2022\"\n}",
  "{\n    \"address\": \"6475 S 1655 E, Salt Lake City, UT 84121\",\n    \"date_sold\": \"Dec 12, 2022\"\n}",
  "{\n    \"address\": \"4788 W Harbor St, West Valley City, UT 84120\",\n    \"date_sold\": \"Dec 12, 2022\"\n}",
  "{\n    \"address\": \"2476 E Cardinal Way, Salt Lake City, UT 84121\",\n    \"date_sold\": \"Dec 12, 2022\"\n}",
  "{\n    \"address\": \"5109 W 5320 S, Salt Lake City, UT 84118\",\n    \"date_sold\": \"Dec 12, 2022\"\n}",
  "{\n    \"address\": \"15023 S Pastoral Way, Bluffdale, UT 84065\",\n    \"date_sold\": \"Dec 12, 2022\"\n}",
  "{\n    \"address\": \"2220 E Murray Holladay Rd Apt 160, Salt Lake City, UT 84117\",\n    \"date_sold\": \"Dec 12, 2022\"\n}",
  "{\n    \"address\": \"181 E 5460 S Apt 1, Salt Lake City, UT 84107\",\n    \"date_sold\": \"Dec 12, 2022\"\n}",
  "{\n    \"address\": \"4931 W 6400 S, West Jordan, UT 84081\",\n    \"date_sold\": \"Dec 12, 2022\"\n}",
  "{\n    \"address\": \"310 E Carole Cir, Salt Lake City, UT 84115\",\n    \"date_sold\": \"Dec 12, 2022\"\n}",
  "{\n    \"address\": \"1549 E Waterbury Dr Unit L, Salt Lake City, UT 84121\",\n    \"date_sold\": \"Dec 12, 2022\"\n}",
  "{\n    \"address\": \"8969 S Flatiron Dr, Sandy, UT 84093\",\n    \"date_sold\": \"Dec 12, 2022\"\n}",
  "{\n    \"address\": \"116 E Resaca Dr Unit F2, Sandy, UT 84070\",\n    \"date_sold\": \"Dec 11, 2022\"\n}",
  "{\n    \"address\": \"2191 E Mabey Dr, Salt Lake City, UT 84109\",\n    \"date_sold\": \"Dec 10, 2022\"\n}",
  "{\n    \"address\": \"10822 S Wynview Ln, South Jordan, UT 84095\",\n    \"date_sold\": \"Dec 10, 2022\"\n}",
  "{\n    \"address\": \"11632 S Scare Crow Ct, South Jordan, UT 84009\",\n    \"date_sold\": \"Dec 10, 2022\"\n}",
  "{\n    \"address\": \"3897 W Fawn Hill Ln, Bluffdale, UT 84065\",\n    \"date_sold\": \"Dec 10, 2022\"\n}",
  "{\n    \"address\": \"11097 S Willow Walk Dr, South Jordan, UT 84009\",\n    \"date_sold\": \"Dec 27, 2022\"\n}",
  "{\n    \"address\": \"761 W Blue Magic Ln Unit 203, Midvale, UT 84047\",\n    \"date_sold\": \"Dec 27, 2022\"\n}",
  "{\n    \"address\": \"12077 E Milona Dr, Draper, UT 84020\",\n    \"date_sold\": \"Dec 22, 2022\"\n}",
  "{\n    \"address\": \"3524 S Blair Cir, South Salt Lake, UT 84115\",\n    \"date_sold\": \"Dec 20, 2022\"\n}",
  "{\n    \"address\": \"1745 W 400 N, Salt Lake City, UT 84116\",\n    \"date_sold\": \"Dec 19, 2022\"\n}",
  "{\n    \"address\": \"7606 S New Sycamore Dr # 170, West Jordan, UT 84081\",\n    \"date_sold\": \"Dec 18, 2022\"\n}",
  "{\n    \"address\": \"7608 S New Sycamore Dr # 169, West Jordan, UT 84081\",\n    \"date_sold\": \"Dec 18, 2022\"\n}",
  "{\n    \"address\": \"7602 S New Sycamore Dr # 172, West Jordan, UT 84081\",\n    \"date_sold\": \"Dec 18, 2022\"\n}",
  "{\n    \"address\": \"6043 W Sparrow View Dr, South Jordan, UT 84009\",\n    \"date_sold\": \"Dec 18, 2022\"\n}",
  "{\n    \"address\": \"7622 S New Sycamore Dr # 176, West Jordan, UT 84081\",\n    \"date_sold\": \"Dec 17, 2022\"\n}",
  "{\n    \"address\": \"1221 W Tamarack Rd, Taylorsville, UT 84123\",\n    \"date_sold\": \"Dec 17, 2022\"\n}",
  "{\n    \"address\": \"5094 S Lambeth St, Taylorsville, UT 84129\",\n    \"date_sold\": \"Dec 15, 2022\"\n}",
  "{\n    \"address\": \"13271 S Sky Ranch Rd, Herriman, UT 84096\",\n    \"date_sold\": \"Dec 15, 2022\"\n}",
  "{\n    \"address\": \"6022 W Folly Island Way # 327, South Jordan, UT 84009\",\n    \"date_sold\": \"Dec 15, 2022\"\n}",
  "{\n    \"address\": \"1469 W California Ave, Salt Lake City, UT 84104\",\n    \"date_sold\": \"Dec 14, 2022\"\n}",
  "{\n    \"address\": \"903 E Lafayette St, Sandy, UT 84094\",\n    \"date_sold\": \"Dec 14, 2022\"\n}",
  "{\n    \"address\": \"5909 W Feldspar Way, West Jordan, UT 84081\",\n    \"date_sold\": \"Dec 14, 2022\"\n}",
  "{\n    \"address\": \"9816 S Kramer Dr, Sandy, UT 84092\",\n    \"date_sold\": \"Dec 14, 2022\"\n}",
  "{\n    \"address\": \"5055 W 3000 S, West Valley City, UT 84120\",\n    \"date_sold\": \"Dec 13, 2022\"\n}",
  "{\n    \"address\": \"6642 W Skip Rock Rd # 433, South Jordan, UT 84009\",\n    \"date_sold\": \"Dec 13, 2022\"\n}",
  "{\n    \"address\": \"3743 W Lilac Heights Dr, South Jordan, UT 84095\",\n    \"date_sold\": \"Dec 13, 2022\"\n}",
  "{\n    \"address\": \"2851 W Teamsters Dr, South Jordan, UT 84095\",\n    \"date_sold\": \"Dec 13, 2022\"\n}",
  "{\n    \"address\": \"10224 S Willamette Way, South Jordan, UT 84009\",\n    \"date_sold\": \"Dec 13, 2022\"\n}",
  "{\n    \"address\": \"650 E 4025 S Unit C, Salt Lake City, UT 84107\",\n    \"date_sold\": \"Dec 13, 2022\"\n}",
  "{\n    \"address\": \"824 E 3950 S Apt C, Salt Lake City, UT 84107\",\n    \"date_sold\": \"Dec 12, 2022\"\n}",
  "{\n    \"address\": \"6475 S 1655 E, Salt Lake City, UT 84121\",\n    \"date_sold\": \"Dec 12, 2022\"\n}",
  "{\n    \"address\": \"2417 W Rustic Roads Dr, South Jordan, UT 84095\",\n    \"date_sold\": \"Dec 12, 2022\"\n}",
  "{\n    \"address\": \"4788 W Harbor St, West Valley City, UT 84120\",\n    \"date_sold\": \"Dec 12, 2022\"\n}",
  "{\n    \"address\": \"2476 E Cardinal Way, Salt Lake City, UT 84121\",\n    \"date_sold\": \"Dec 12, 2022\"\n}",
  "{\n    \"address\": \"2220 E Murray Holladay Rd Apt 160, Salt Lake City, UT 84117\",\n    \"date_sold\": \"Dec 12, 2022\"\n}",
  "{\n    \"address\": \"15023 S Pastoral Way, Bluffdale, UT 84065\",\n    \"date_sold\": \"Dec 12, 2022\"\n}",
  "{\n    \"address\": \"5109 W 5320 S, Salt Lake City, UT 84118\",\n    \"date_sold\": \"Dec 12, 2022\"\n}",
  "{\n    \"address\": \"181 E 5460 S Apt 1, Salt Lake City, UT 84107\",\n    \"date_sold\": \"Dec 12, 2022\"\n}",
  "{\n    \"address\": \"4931 W 6400 S, West Jordan, UT 84081\",\n    \"date_sold\": \"Dec 12, 2022\"\n}",
  "{\n    \"address\": \"310 E Carole Cir, Salt Lake City, UT 84115\",\n    \"date_sold\": \"Dec 12, 2022\"\n}",
  "{\n    \"address\": \"1549 E Waterbury Dr Unit L, Salt Lake City, UT 84121\",\n    \"date_sold\": \"Dec 12, 2022\"\n}",
  "{\n    \"address\": \"8969 S Flatiron Dr, Sandy, UT 84093\",\n    \"date_sold\": \"Dec 12, 2022\"\n}",
  "{\n    \"address\": \"116 E Resaca Dr Unit F2, Sandy, UT 84070\",\n    \"date_sold\": \"Dec 11, 2022\"\n}",
  "{\n    \"address\": \"10822 S Wynview Ln, South Jordan, UT 84095\",\n    \"date_sold\": \"Dec 10, 2022\"\n}",
  "{\n    \"address\": \"2191 E Mabey Dr, Salt Lake City, UT 84109\",\n    \"date_sold\": \"Dec 10, 2022\"\n}",
  "{\n    \"address\": \"11632 S Scare Crow Ct, South Jordan, UT 84009\",\n    \"date_sold\": \"Dec 10, 2022\"\n}",
  "{\n    \"address\": \"3897 W Fawn Hill Ln, Bluffdale, UT 84065\",\n    \"date_sold\": \"Dec 10, 2022\"\n}",
  "{\n    \"address\": \"11097 S Willow Walk Dr, South Jordan, UT 84009\",\n    \"date_sold\": \"Dec 27, 2022\"\n}",
  "{\n    \"address\": \"761 W Blue Magic Ln Unit 203, Midvale, UT 84047\",\n    \"date_sold\": \"Dec 27, 2022\"\n}",
  "{\n    \"address\": \"12077 E Milona Dr, Draper, UT 84020\",\n    \"date_sold\": \"Dec 22, 2022\"\n}",
  "{\n    \"address\": \"3524 S Blair Cir, South Salt Lake, UT 84115\",\n    \"date_sold\": \"Dec 20, 2022\"\n}",
  "{\n    \"address\": \"1745 W 400 N, Salt Lake City, UT 84116\",\n    \"date_sold\": \"Dec 19, 2022\"\n}",
  "{\n    \"address\": \"7606 S New Sycamore Dr # 170, West Jordan, UT 84081\",\n    \"date_sold\": \"Dec 18, 2022\"\n}",
  "{\n    \"address\": \"7608 S New Sycamore Dr # 169, West Jordan, UT 84081\",\n    \"date_sold\": \"Dec 18, 2022\"\n}",
  "{\n    \"address\": \"7602 S New Sycamore Dr # 172, West Jordan, UT 84081\",\n    \"date_sold\": \"Dec 18, 2022\"\n}",
  "{\n    \"address\": \"6043 W Sparrow View Dr, South Jordan, UT 84009\",\n    \"date_sold\": \"Dec 18, 2022\"\n}",
  "{\n    \"address\": \"7622 S New Sycamore Dr # 176, West Jordan, UT 84081\",\n    \"date_sold\": \"Dec 17, 2022\"\n}",
  "{\n    \"address\": \"1221 W Tamarack Rd, Taylorsville, UT 84123\",\n    \"date_sold\": \"Dec 17, 2022\"\n}",
  "{\n    \"address\": \"5094 S Lambeth St, Taylorsville, UT 84129\",\n    \"date_sold\": \"Dec 15, 2022\"\n}",
  "{\n    \"address\": \"13271 S Sky Ranch Rd, Herriman, UT 84096\",\n    \"date_sold\": \"Dec 15, 2022\"\n}",
  "{\n    \"address\": \"6022 W Folly Island Way # 327, South Jordan, UT 84009\",\n    \"date_sold\": \"Dec 15, 2022\"\n}",
  "{\n    \"address\": \"1469 W California Ave, Salt Lake City, UT 84104\",\n    \"date_sold\": \"Dec 14, 2022\"\n}",
  "{\n    \"address\": \"903 E Lafayette St, Sandy, UT 84094\",\n    \"date_sold\": \"Dec 14, 2022\"\n}",
  "{\n    \"address\": \"5909 W Feldspar Way, West Jordan, UT 84081\",\n    \"date_sold\": \"Dec 14, 2022\"\n}",
  "{\n    \"address\": \"9816 S Kramer Dr, Sandy, UT 84092\",\n    \"date_sold\": \"Dec 14, 2022\"\n}",
  "{\n    \"address\": \"5055 W 3000 S, West Valley City, UT 84120\",\n    \"date_sold\": \"Dec 13, 2022\"\n}",
  "{\n    \"address\": \"6642 W Skip Rock Rd # 433, South Jordan, UT 84009\",\n    \"date_sold\": \"Dec 13, 2022\"\n}",
  "{\n    \"address\": \"3743 W Lilac Heights Dr, South Jordan, UT 84095\",\n    \"date_sold\": \"Dec 13, 2022\"\n}",
  "{\n    \"address\": \"2851 W Teamsters Dr, South Jordan, UT 84095\",\n    \"date_sold\": \"Dec 13, 2022\"\n}",
  "{\n    \"address\": \"10224 S Willamette Way, South Jordan, UT 84009\",\n    \"date_sold\": \"Dec 13, 2022\"\n}",
  "{\n    \"address\": \"650 E 4025 S Unit C, Salt Lake City, UT 84107\",\n    \"date_sold\": \"Dec 13, 2022\"\n}",
  "{\n    \"address\": \"824 E 3950 S Apt C, Salt Lake City, UT 84107\",\n    \"date_sold\": \"Dec 12, 2022\"\n}",
  "{\n    \"address\": \"6475 S 1655 E, Salt Lake City, UT 84121\",\n    \"date_sold\": \"Dec 12, 2022\"\n}",
  "{\n    \"address\": \"2417 W Rustic Roads Dr, South Jordan, UT 84095\",\n    \"date_sold\": \"Dec 12, 2022\"\n}",
  "{\n    \"address\": \"4788 W Harbor St, West Valley City, UT 84120\",\n    \"date_sold\": \"Dec 12, 2022\"\n}",
  "{\n    \"address\": \"2476 E Cardinal Way, Salt Lake City, UT 84121\",\n    \"date_sold\": \"Dec 12, 2022\"\n}",
  "{\n    \"address\": \"2220 E Murray Holladay Rd Apt 160, Salt Lake City, UT 84117\",\n    \"date_sold\": \"Dec 12, 2022\"\n}",
  "{\n    \"address\": \"15023 S Pastoral Way, Bluffdale, UT 84065\",\n    \"date_sold\": \"Dec 12, 2022\"\n}",
  "{\n    \"address\": \"5109 W 5320 S, Salt Lake City, UT 84118\",\n    \"date_sold\": \"Dec 12, 2022\"\n}",
  "{\n    \"address\": \"181 E 5460 S Apt 1, Salt Lake City, UT 84107\",\n    \"date_sold\": \"Dec 12, 2022\"\n}",
  "{\n    \"address\": \"4931 W 6400 S, West Jordan, UT 84081\",\n    \"date_sold\": \"Dec 12, 2022\"\n}",
  "{\n    \"address\": \"310 E Carole Cir, Salt Lake City, UT 84115\",\n    \"date_sold\": \"Dec 12, 2022\"\n}",
  "{\n    \"address\": \"1549 E Waterbury Dr Unit L, Salt Lake City, UT 84121\",\n    \"date_sold\": \"Dec 12, 2022\"\n}",
  "{\n    \"address\": \"8969 S Flatiron Dr, Sandy, UT 84093\",\n    \"date_sold\": \"Dec 12, 2022\"\n}",
  "{\n    \"address\": \"116 E Resaca Dr Unit F2, Sandy, UT 84070\",\n    \"date_sold\": \"Dec 11, 2022\"\n}",
  "{\n    \"address\": \"10822 S Wynview Ln, South Jordan, UT 84095\",\n    \"date_sold\": \"Dec 10, 2022\"\n}",
  "{\n    \"address\": \"2191 E Mabey Dr, Salt Lake City, UT 84109\",\n    \"date_sold\": \"Dec 10, 2022\"\n}",
  "{\n    \"address\": \"11632 S Scare Crow Ct, South Jordan, UT 84009\",\n    \"date_sold\": \"Dec 10, 2022\"\n}",
  "{\n    \"address\": \"3897 W Fawn Hill Ln, Bluffdale, UT 84065\",\n    \"date_sold\": \"Dec 10, 2022\"\n}",
  "{\n    \"address\": \"11097 S Willow Walk Dr, South Jordan, UT 84009\",\n    \"date_sold\": \"Dec 27, 2022\"\n}",
  "{\n    \"address\": \"761 W Blue Magic Ln Unit 203, Midvale, UT 84047\",\n    \"date_sold\": \"Dec 27, 2022\"\n}",
  "{\n    \"address\": \"12077 E Milona Dr, Draper, UT 84020\",\n    \"date_sold\": \"Dec 22, 2022\"\n}",
  "{\n    \"address\": \"3524 S Blair Cir, South Salt Lake, UT 84115\",\n    \"date_sold\": \"Dec 20, 2022\"\n}",
  "{\n    \"address\": \"1745 W 400 N, Salt Lake City, UT 84116\",\n    \"date_sold\": \"Dec 19, 2022\"\n}",
  "{\n    \"address\": \"7606 S New Sycamore Dr # 170, West Jordan, UT 84081\",\n    \"date_sold\": \"Dec 18, 2022\"\n}",
  "{\n    \"address\": \"7608 S New Sycamore Dr # 169, West Jordan, UT 84081\",\n    \"date_sold\": \"Dec 18, 2022\"\n}",
  "{\n    \"address\": \"7602 S New Sycamore Dr # 172, West Jordan, UT 84081\",\n    \"date_sold\": \"Dec 18, 2022\"\n}",
  "{\n    \"address\": \"6043 W Sparrow View Dr, South Jordan, UT 84009\",\n    \"date_sold\": \"Dec 18, 2022\"\n}",
  "{\n    \"address\": \"7622 S New Sycamore Dr # 176, West Jordan, UT 84081\",\n    \"date_sold\": \"Dec 17, 2022\"\n}",
  "{\n    \"address\": \"1221 W Tamarack Rd, Taylorsville, UT 84123\",\n    \"date_sold\": \"Dec 17, 2022\"\n}",
  "{\n    \"address\": \"5094 S Lambeth St, Taylorsville, UT 84129\",\n    \"date_sold\": \"Dec 15, 2022\"\n}",
  "{\n    \"address\": \"6022 W Folly Island Way # 327, South Jordan, UT 84009\",\n    \"date_sold\": \"Dec 15, 2022\"\n}",
  "{\n    \"address\": \"13271 S Sky Ranch Rd, Herriman, UT 84096\",\n    \"date_sold\": \"Dec 15, 2022\"\n}",
  "{\n    \"address\": \"903 E Lafayette St, Sandy, UT 84094\",\n    \"date_sold\": \"Dec 14, 2022\"\n}",
  "{\n    \"address\": \"1469 W California Ave, Salt Lake City, UT 84104\",\n    \"date_sold\": \"Dec 14, 2022\"\n}",
  "{\n    \"address\": \"5909 W Feldspar Way, West Jordan, UT 84081\",\n    \"date_sold\": \"Dec 14, 2022\"\n}",
  "{\n    \"address\": \"9816 S Kramer Dr, Sandy, UT 84092\",\n    \"date_sold\": \"Dec 14, 2022\"\n}",
  "{\n    \"address\": \"5055 W 3000 S, West Valley City, UT 84120\",\n    \"date_sold\": \"Dec 13, 2022\"\n}",
  "{\n    \"address\": \"6642 W Skip Rock Rd # 433, South Jordan, UT 84009\",\n    \"date_sold\": \"Dec 13, 2022\"\n}",
  "{\n    \"address\": \"3743 W Lilac Heights Dr, South Jordan, UT 84095\",\n    \"date_sold\": \"Dec 13, 2022\"\n}",
  "{\n    \"address\": \"2851 W Teamsters Dr, South Jordan, UT 84095\",\n    \"date_sold\": \"Dec 13, 2022\"\n}",
  "{\n    \"address\": \"10224 S Willamette Way, South Jordan, UT 84009\",\n    \"date_sold\": \"Dec 13, 2022\"\n}",
  "{\n    \"address\": \"650 E 4025 S Unit C, Salt Lake City, UT 84107\",\n    \"date_sold\": \"Dec 13, 2022\"\n}",
  "{\n    \"address\": \"824 E 3950 S Apt C, Salt Lake City, UT 84107\",\n    \"date_sold\": \"Dec 12, 2022\"\n}",
  "{\n    \"address\": \"2417 W Rustic Roads Dr, South Jordan, UT 84095\",\n    \"date_sold\": \"Dec 12, 2022\"\n}",
  "{\n    \"address\": \"6475 S 1655 E, Salt Lake City, UT 84121\",\n    \"date_sold\": \"Dec 12, 2022\"\n}",
  "{\n    \"address\": \"4788 W Harbor St, West Valley City, UT 84120\",\n    \"date_sold\": \"Dec 12, 2022\"\n}",
  "{\n    \"address\": \"2476 E Cardinal Way, Salt Lake City, UT 84121\",\n    \"date_sold\": \"Dec 12, 2022\"\n}",
  "{\n    \"address\": \"5109 W 5320 S, Salt Lake City, UT 84118\",\n    \"date_sold\": \"Dec 12, 2022\"\n}",
  "{\n    \"address\": \"15023 S Pastoral Way, Bluffdale, UT 84065\",\n    \"date_sold\": \"Dec 12, 2022\"\n}",
  "{\n    \"address\": \"2220 E Murray Holladay Rd Apt 160, Salt Lake City, UT 84117\",\n    \"date_sold\": \"Dec 12, 2022\"\n}",
  "{\n    \"address\": \"181 E 5460 S Apt 1, Salt Lake City, UT 84107\",\n    \"date_sold\": \"Dec 12, 2022\"\n}",
  "{\n    \"address\": \"4931 W 6400 S, West Jordan, UT 84081\",\n    \"date_sold\": \"Dec 12, 2022\"\n}",
  "{\n    \"address\": \"310 E Carole Cir, Salt Lake City, UT 84115\",\n    \"date_sold\": \"Dec 12, 2022\"\n}",
  "{\n    \"address\": \"8969 S Flatiron Dr, Sandy, UT 84093\",\n    \"date_sold\": \"Dec 12, 2022\"\n}",
  "{\n    \"address\": \"1549 E Waterbury Dr Unit L, Salt Lake City, UT 84121\",\n    \"date_sold\": \"Dec 12, 2022\"\n}",
  "{\n    \"address\": \"116 E Resaca Dr Unit F2, Sandy, UT 84070\",\n    \"date_sold\": \"Dec 11, 2022\"\n}",
  "{\n    \"address\": \"2191 E Mabey Dr, Salt Lake City, UT 84109\",\n    \"date_sold\": \"Dec 10, 2022\"\n}",
  "{\n    \"address\": \"10822 S Wynview Ln, South Jordan, UT 84095\",\n    \"date_sold\": \"Dec 10, 2022\"\n}",
  "{\n    \"address\": \"11632 S Scare Crow Ct, South Jordan, UT 84009\",\n    \"date_sold\": \"Dec 10, 2022\"\n}",
  "{\n    \"address\": \"3897 W Fawn Hill Ln, Bluffdale, UT 84065\",\n    \"date_sold\": \"Dec 10, 2022\"\n}",
  "{\n    \"address\": \"11097 S Willow Walk Dr, South Jordan, UT 84009\",\n    \"date_sold\": \"Dec 27, 2022\"\n}",
  "{\n    \"address\": \"761 W Blue Magic Ln Unit 203, Midvale, UT 84047\",\n    \"date_sold\": \"Dec 27, 2022\"\n}",
  "{\n    \"address\": \"12077 E Milona Dr, Draper, UT 84020\",\n    \"date_sold\": \"Dec 22, 2022\"\n}",
  "{\n    \"address\": \"3524 S Blair Cir, South Salt Lake, UT 84115\",\n    \"date_sold\": \"Dec 20, 2022\"\n}",
  "{\n    \"address\": \"1745 W 400 N, Salt Lake City, UT 84116\",\n    \"date_sold\": \"Dec 19, 2022\"\n}",
  "{\n    \"address\": \"7606 S New Sycamore Dr # 170, West Jordan, UT 84081\",\n    \"date_sold\": \"Dec 18, 2022\"\n}",
  "{\n    \"address\": \"7608 S New Sycamore Dr # 169, West Jordan, UT 84081\",\n    \"date_sold\": \"Dec 18, 2022\"\n}",
  "{\n    \"address\": \"7602 S New Sycamore Dr # 172, West Jordan, UT 84081\",\n    \"date_sold\": \"Dec 18, 2022\"\n}",
  "{\n    \"address\": \"6043 W Sparrow View Dr, South Jordan, UT 84009\",\n    \"date_sold\": \"Dec 18, 2022\"\n}",
  "{\n    \"address\": \"7622 S New Sycamore Dr # 176, West Jordan, UT 84081\",\n    \"date_sold\": \"Dec 17, 2022\"\n}",
  "{\n    \"address\": \"1221 W Tamarack Rd, Taylorsville, UT 84123\",\n    \"date_sold\": \"Dec 17, 2022\"\n}",
  "{\n    \"address\": \"5094 S Lambeth St, Taylorsville, UT 84129\",\n    \"date_sold\": \"Dec 15, 2022\"\n}",
  "{\n    \"address\": \"6022 W Folly Island Way # 327, South Jordan, UT 84009\",\n    \"date_sold\": \"Dec 15, 2022\"\n}",
  "{\n    \"address\": \"13271 S Sky Ranch Rd, Herriman, UT 84096\",\n    \"date_sold\": \"Dec 15, 2022\"\n}",
  "{\n    \"address\": \"1469 W California Ave, Salt Lake City, UT 84104\",\n    \"date_sold\": \"Dec 14, 2022\"\n}",
  "{\n    \"address\": \"903 E Lafayette St, Sandy, UT 84094\",\n    \"date_sold\": \"Dec 14, 2022\"\n}",
  "{\n    \"address\": \"5909 W Feldspar Way, West Jordan, UT 84081\",\n    \"date_sold\": \"Dec 14, 2022\"\n}",
  "{\n    \"address\": \"9816 S Kramer Dr, Sandy, UT 84092\",\n    \"date_sold\": \"Dec 14, 2022\"\n}",
  "{\n    \"address\": \"5055 W 3000 S, West Valley City, UT 84120\",\n    \"date_sold\": \"Dec 13, 2022\"\n}",
  "{\n    \"address\": \"6642 W Skip Rock Rd # 433, South Jordan, UT 84009\",\n    \"date_sold\": \"Dec 13, 2022\"\n}",
  "{\n    \"address\": \"3743 W Lilac Heights Dr, South Jordan, UT 84095\",\n    \"date_sold\": \"Dec 13, 2022\"\n}",
  "{\n    \"address\": \"2851 W Teamsters Dr, South Jordan, UT 84095\",\n    \"date_sold\": \"Dec 13, 2022\"\n}",
  "{\n    \"address\": \"10224 S Willamette Way, South Jordan, UT 84009\",\n    \"date_sold\": \"Dec 13, 2022\"\n}",
  "{\n    \"address\": \"650 E 4025 S Unit C, Salt Lake City, UT 84107\",\n    \"date_sold\": \"Dec 13, 2022\"\n}",
  "{\n    \"address\": \"824 E 3950 S Apt C, Salt Lake City, UT 84107\",\n    \"date_sold\": \"Dec 12, 2022\"\n}",
  "{\n    \"address\": \"6475 S 1655 E, Salt Lake City, UT 84121\",\n    \"date_sold\": \"Dec 12, 2022\"\n}",
  "{\n    \"address\": \"2417 W Rustic Roads Dr, South Jordan, UT 84095\",\n    \"date_sold\": \"Dec 12, 2022\"\n}",
  "{\n    \"address\": \"4788 W Harbor St, West Valley City, UT 84120\",\n    \"date_sold\": \"Dec 12, 2022\"\n}",
  "{\n    \"address\": \"2476 E Cardinal Way, Salt Lake City, UT 84121\",\n    \"date_sold\": \"Dec 12, 2022\"\n}",
  "{\n    \"address\": \"2220 E Murray Holladay Rd Apt 160, Salt Lake City, UT 84117\",\n    \"date_sold\": \"Dec 12, 2022\"\n}",
  "{\n    \"address\": \"15023 S Pastoral Way, Bluffdale, UT 84065\",\n    \"date_sold\": \"Dec 12, 2022\"\n}",
  "{\n    \"address\": \"5109 W 5320 S, Salt Lake City, UT 84118\",\n    \"date_sold\": \"Dec 12, 2022\"\n}",
  "{\n    \"address\": \"181 E 5460 S Apt 1, Salt Lake City, UT 84107\",\n    \"date_sold\": \"Dec 12, 2022\"\n}",
  "{\n    \"address\": \"4931 W 6400 S, West Jordan, UT 84081\",\n    \"date_sold\": \"Dec 12, 2022\"\n}",
  "{\n    \"address\": \"310 E Carole Cir, Salt Lake City, UT 84115\",\n    \"date_sold\": \"Dec 12, 2022\"\n}",
  "{\n    \"address\": \"8969 S Flatiron Dr, Sandy, UT 84093\",\n    \"date_sold\": \"Dec 12, 2022\"\n}",
  "{\n    \"address\": \"1549 E Waterbury Dr Unit L, Salt Lake City, UT 84121\",\n    \"date_sold\": \"Dec 12, 2022\"\n}",
  "{\n    \"address\": \"116 E Resaca Dr Unit F2, Sandy, UT 84070\",\n    \"date_sold\": \"Dec 11, 2022\"\n}",
  "{\n    \"address\": \"10822 S Wynview Ln, South Jordan, UT 84095\",\n    \"date_sold\": \"Dec 10, 2022\"\n}",
  "{\n    \"address\": \"2191 E Mabey Dr, Salt Lake City, UT 84109\",\n    \"date_sold\": \"Dec 10, 2022\"\n}",
  "{\n    \"address\": \"11632 S Scare Crow Ct, South Jordan, UT 84009\",\n    \"date_sold\": \"Dec 10, 2022\"\n}",
  "{\n    \"address\": \"3897 W Fawn Hill Ln, Bluffdale, UT 84065\",\n    \"date_sold\": \"Dec 10, 2022\"\n}",
  "{\n    \"address\": \"11097 S Willow Walk Dr, South Jordan, UT 84009\",\n    \"date_sold\": \"Dec 27, 2022\"\n}",
  "{\n    \"address\": \"761 W Blue Magic Ln Unit 203, Midvale, UT 84047\",\n    \"date_sold\": \"Dec 27, 2022\"\n}",
  "{\n    \"address\": \"12077 E Milona Dr, Draper, UT 84020\",\n    \"date_sold\": \"Dec 22, 2022\"\n}",
  "{\n    \"address\": \"3524 S Blair Cir, South Salt Lake, UT 84115\",\n    \"date_sold\": \"Dec 20, 2022\"\n}",
  "{\n    \"address\": \"1745 W 400 N, Salt Lake City, UT 84116\",\n    \"date_sold\": \"Dec 19, 2022\"\n}",
  "{\n    \"address\": \"7606 S New Sycamore Dr # 170, West Jordan, UT 84081\",\n    \"date_sold\": \"Dec 18, 2022\"\n}",
  "{\n    \"address\": \"7608 S New Sycamore Dr # 169, West Jordan, UT 84081\",\n    \"date_sold\": \"Dec 18, 2022\"\n}",
  "{\n    \"address\": \"7602 S New Sycamore Dr # 172, West Jordan, UT 84081\",\n    \"date_sold\": \"Dec 18, 2022\"\n}",
  "{\n    \"address\": \"6043 W Sparrow View Dr, South Jordan, UT 84009\",\n    \"date_sold\": \"Dec 18, 2022\"\n}",
  "{\n    \"address\": \"7622 S New Sycamore Dr # 176, West Jordan, UT 84081\",\n    \"date_sold\": \"Dec 17, 2022\"\n}",
  "{\n    \"address\": \"1221 W Tamarack Rd, Taylorsville, UT 84123\",\n    \"date_sold\": \"Dec 17, 2022\"\n}",
  "{\n    \"address\": \"5094 S Lambeth St, Taylorsville, UT 84129\",\n    \"date_sold\": \"Dec 15, 2022\"\n}",
  "{\n    \"address\": \"13271 S Sky Ranch Rd, Herriman, UT 84096\",\n    \"date_sold\": \"Dec 15, 2022\"\n}",
  "{\n    \"address\": \"6022 W Folly Island Way # 327, South Jordan, UT 84009\",\n    \"date_sold\": \"Dec 15, 2022\"\n}",
  "{\n    \"address\": \"903 E Lafayette St, Sandy, UT 84094\",\n    \"date_sold\": \"Dec 14, 2022\"\n}",
  "{\n    \"address\": \"1469 W California Ave, Salt Lake City, UT 84104\",\n    \"date_sold\": \"Dec 14, 2022\"\n}",
  "{\n    \"address\": \"5909 W Feldspar Way, West Jordan, UT 84081\",\n    \"date_sold\": \"Dec 14, 2022\"\n}",
  "{\n    \"address\": \"9816 S Kramer Dr, Sandy, UT 84092\",\n    \"date_sold\": \"Dec 14, 2022\"\n}",
  "{\n    \"address\": \"5055 W 3000 S, West Valley City, UT 84120\",\n    \"date_sold\": \"Dec 13, 2022\"\n}",
  "{\n    \"address\": \"6642 W Skip Rock Rd # 433, South Jordan, UT 84009\",\n    \"date_sold\": \"Dec 13, 2022\"\n}",
  "{\n    \"address\": \"3743 W Lilac Heights Dr, South Jordan, UT 84095\",\n    \"date_sold\": \"Dec 13, 2022\"\n}",
  "{\n    \"address\": \"2851 W Teamsters Dr, South Jordan, UT 84095\",\n    \"date_sold\": \"Dec 13, 2022\"\n}",
  "{\n    \"address\": \"10224 S Willamette Way, South Jordan, UT 84009\",\n    \"date_sold\": \"Dec 13, 2022\"\n}",
  "{\n    \"address\": \"650 E 4025 S Unit C, Salt Lake City, UT 84107\",\n    \"date_sold\": \"Dec 13, 2022\"\n}",
  "{\n    \"address\": \"824 E 3950 S Apt C, Salt Lake City, UT 84107\",\n    \"date_sold\": \"Dec 12, 2022\"\n}",
  "{\n    \"address\": \"2417 W Rustic Roads Dr, South Jordan, UT 84095\",\n    \"date_sold\": \"Dec 12, 2022\"\n}",
  "{\n    \"address\": \"6475 S 1655 E, Salt Lake City, UT 84121\",\n    \"date_sold\": \"Dec 12, 2022\"\n}",
  "{\n    \"address\": \"4788 W Harbor St, West Valley City, UT 84120\",\n    \"date_sold\": \"Dec 12, 2022\"\n}",
  "{\n    \"address\": \"2476 E Cardinal Way, Salt Lake City, UT 84121\",\n    \"date_sold\": \"Dec 12, 2022\"\n}",
  "{\n    \"address\": \"5109 W 5320 S, Salt Lake City, UT 84118\",\n    \"date_sold\": \"Dec 12, 2022\"\n}",
  "{\n    \"address\": \"15023 S Pastoral Way, Bluffdale, UT 84065\",\n    \"date_sold\": \"Dec 12, 2022\"\n}",
  "{\n    \"address\": \"2220 E Murray Holladay Rd Apt 160, Salt Lake City, UT 84117\",\n    \"date_sold\": \"Dec 12, 2022\"\n}",
  "{\n    \"address\": \"181 E 5460 S Apt 1, Salt Lake City, UT 84107\",\n    \"date_sold\": \"Dec 12, 2022\"\n}",
  "{\n    \"address\": \"4931 W 6400 S, West Jordan, UT 84081\",\n    \"date_sold\": \"Dec 12, 2022\"\n}",
  "{\n    \"address\": \"310 E Carole Cir, Salt Lake City, UT 84115\",\n    \"date_sold\": \"Dec 12, 2022\"\n}",
  "{\n    \"address\": \"1549 E Waterbury Dr Unit L, Salt Lake City, UT 84121\",\n    \"date_sold\": \"Dec 12, 2022\"\n}",
  "{\n    \"address\": \"8969 S Flatiron Dr, Sandy, UT 84093\",\n    \"date_sold\": \"Dec 12, 2022\"\n}",
  "{\n    \"address\": \"116 E Resaca Dr Unit F2, Sandy, UT 84070\",\n    \"date_sold\": \"Dec 11, 2022\"\n}",
  "{\n    \"address\": \"2191 E Mabey Dr, Salt Lake City, UT 84109\",\n    \"date_sold\": \"Dec 10, 2022\"\n}",
  "{\n    \"address\": \"10822 S Wynview Ln, South Jordan, UT 84095\",\n    \"date_sold\": \"Dec 10, 2022\"\n}",
  "{\n    \"address\": \"11632 S Scare Crow Ct, South Jordan, UT 84009\",\n    \"date_sold\": \"Dec 10, 2022\"\n}",
  "{\n    \"address\": \"3897 W Fawn Hill Ln, Bluffdale, UT 84065\",\n    \"date_sold\": \"Dec 10, 2022\"\n}",
  "{\n    \"address\": \"11097 S Willow Walk Dr, South Jordan, UT 84009\",\n    \"date_sold\": \"Dec 27, 2022\"\n}",
  "{\n    \"address\": \"761 W Blue Magic Ln Unit 203, Midvale, UT 84047\",\n    \"date_sold\": \"Dec 27, 2022\"\n}",
  "{\n    \"address\": \"12077 E Milona Dr, Draper, UT 84020\",\n    \"date_sold\": \"Dec 22, 2022\"\n}",
  "{\n    \"address\": \"3524 S Blair Cir, South Salt Lake, UT 84115\",\n    \"date_sold\": \"Dec 20, 2022\"\n}",
  "{\n    \"address\": \"1745 W 400 N, Salt Lake City, UT 84116\",\n    \"date_sold\": \"Dec 19, 2022\"\n}",
  "{\n    \"address\": \"7606 S New Sycamore Dr # 170, West Jordan, UT 84081\",\n    \"date_sold\": \"Dec 18, 2022\"\n}",
  "{\n    \"address\": \"7608 S New Sycamore Dr # 169, West Jordan, UT 84081\",\n    \"date_sold\": \"Dec 18, 2022\"\n}",
  "{\n    \"address\": \"7602 S New Sycamore Dr # 172, West Jordan, UT 84081\",\n    \"date_sold\": \"Dec 18, 2022\"\n}",
  "{\n    \"address\": \"6043 W Sparrow View Dr, South Jordan, UT 84009\",\n    \"date_sold\": \"Dec 18, 2022\"\n}",
  "{\n    \"address\": \"7622 S New Sycamore Dr # 176, West Jordan, UT 84081\",\n    \"date_sold\": \"Dec 17, 2022\"\n}",
  "{\n    \"address\": \"1221 W Tamarack Rd, Taylorsville, UT 84123\",\n    \"date_sold\": \"Dec 17, 2022\"\n}",
  "{\n    \"address\": \"5094 S Lambeth St, Taylorsville, UT 84129\",\n    \"date_sold\": \"Dec 15, 2022\"\n}",
  "{\n    \"address\": \"6022 W Folly Island Way # 327, South Jordan, UT 84009\",\n    \"date_sold\": \"Dec 15, 2022\"\n}",
  "{\n    \"address\": \"13271 S Sky Ranch Rd, Herriman, UT 84096\",\n    \"date_sold\": \"Dec 15, 2022\"\n}",
  "{\n    \"address\": \"1469 W California Ave, Salt Lake City, UT 84104\",\n    \"date_sold\": \"Dec 14, 2022\"\n}",
  "{\n    \"address\": \"903 E Lafayette St, Sandy, UT 84094\",\n    \"date_sold\": \"Dec 14, 2022\"\n}",
  "{\n    \"address\": \"5909 W Feldspar Way, West Jordan, UT 84081\",\n    \"date_sold\": \"Dec 14, 2022\"\n}",
  "{\n    \"address\": \"9816 S Kramer Dr, Sandy, UT 84092\",\n    \"date_sold\": \"Dec 14, 2022\"\n}",
  "{\n    \"address\": \"5055 W 3000 S, West Valley City, UT 84120\",\n    \"date_sold\": \"Dec 13, 2022\"\n}",
  "{\n    \"address\": \"6642 W Skip Rock Rd # 433, South Jordan, UT 84009\",\n    \"date_sold\": \"Dec 13, 2022\"\n}",
  "{\n    \"address\": \"3743 W Lilac Heights Dr, South Jordan, UT 84095\",\n    \"date_sold\": \"Dec 13, 2022\"\n}",
  "{\n    \"address\": \"2851 W Teamsters Dr, South Jordan, UT 84095\",\n    \"date_sold\": \"Dec 13, 2022\"\n}",
  "{\n    \"address\": \"10224 S Willamette Way, South Jordan, UT 84009\",\n    \"date_sold\": \"Dec 13, 2022\"\n}",
  "{\n    \"address\": \"650 E 4025 S Unit C, Salt Lake City, UT 84107\",\n    \"date_sold\": \"Dec 13, 2022\"\n}",
  "{\n    \"address\": \"824 E 3950 S Apt C, Salt Lake City, UT 84107\",\n    \"date_sold\": \"Dec 12, 2022\"\n}",
  "{\n    \"address\": \"6475 S 1655 E, Salt Lake City, UT 84121\",\n    \"date_sold\": \"Dec 12, 2022\"\n}",
  "{\n    \"address\": \"2417 W Rustic Roads Dr, South Jordan, UT 84095\",\n    \"date_sold\": \"Dec 12, 2022\"\n}",
  "{\n    \"address\": \"4788 W Harbor St, West Valley City, UT 84120\",\n    \"date_sold\": \"Dec 12, 2022\"\n}",
  "{\n    \"address\": \"2476 E Cardinal Way, Salt Lake City, UT 84121\",\n    \"date_sold\": \"Dec 12, 2022\"\n}",
  "{\n    \"address\": \"5109 W 5320 S, Salt Lake City, UT 84118\",\n    \"date_sold\": \"Dec 12, 2022\"\n}",
  "{\n    \"address\": \"15023 S Pastoral Way, Bluffdale, UT 84065\",\n    \"date_sold\": \"Dec 12, 2022\"\n}",
  "{\n    \"address\": \"2220 E Murray Holladay Rd Apt 160, Salt Lake City, UT 84117\",\n    \"date_sold\": \"Dec 12, 2022\"\n}",
  "{\n    \"address\": \"181 E 5460 S Apt 1, Salt Lake City, UT 84107\",\n    \"date_sold\": \"Dec 12, 2022\"\n}",
  "{\n    \"address\": \"4931 W 6400 S, West Jordan, UT 84081\",\n    \"date_sold\": \"Dec 12, 2022\"\n}",
  "{\n    \"address\": \"310 E Carole Cir, Salt Lake City, UT 84115\",\n    \"date_sold\": \"Dec 12, 2022\"\n}",
  "{\n    \"address\": \"8969 S Flatiron Dr, Sandy, UT 84093\",\n    \"date_sold\": \"Dec 12, 2022\"\n}",
  "{\n    \"address\": \"1549 E Waterbury Dr Unit L, Salt Lake City, UT 84121\",\n    \"date_sold\": \"Dec 12, 2022\"\n}",
  "{\n    \"address\": \"116 E Resaca Dr Unit F2, Sandy, UT 84070\",\n    \"date_sold\": \"Dec 11, 2022\"\n}",
  "{\n    \"address\": \"2191 E Mabey Dr, Salt Lake City, UT 84109\",\n    \"date_sold\": \"Dec 10, 2022\"\n}",
  "{\n    \"address\": \"10822 S Wynview Ln, South Jordan, UT 84095\",\n    \"date_sold\": \"Dec 10, 2022\"\n}",
  "{\n    \"address\": \"11632 S Scare Crow Ct, South Jordan, UT 84009\",\n    \"date_sold\": \"Dec 10, 2022\"\n}",
  "{\n    \"address\": \"3897 W Fawn Hill Ln, Bluffdale, UT 84065\",\n    \"date_sold\": \"Dec 10, 2022\"\n}",
  "{\n    \"address\": \"11097 S Willow Walk Dr, South Jordan, UT 84009\",\n    \"date_sold\": \"Dec 27, 2022\"\n}",
  "{\n    \"address\": \"761 W Blue Magic Ln Unit 203, Midvale, UT 84047\",\n    \"date_sold\": \"Dec 27, 2022\"\n}",
  "{\n    \"address\": \"12077 E Milona Dr, Draper, UT 84020\",\n    \"date_sold\": \"Dec 22, 2022\"\n}",
  "{\n    \"address\": \"3524 S Blair Cir, South Salt Lake, UT 84115\",\n    \"date_sold\": \"Dec 20, 2022\"\n}",
  "{\n    \"address\": \"1745 W 400 N, Salt Lake City, UT 84116\",\n    \"date_sold\": \"Dec 19, 2022\"\n}",
  "{\n    \"address\": \"7606 S New Sycamore Dr # 170, West Jordan, UT 84081\",\n    \"date_sold\": \"Dec 18, 2022\"\n}",
  "{\n    \"address\": \"7608 S New Sycamore Dr # 169, West Jordan, UT 84081\",\n    \"date_sold\": \"Dec 18, 2022\"\n}",
  "{\n    \"address\": \"7602 S New Sycamore Dr # 172, West Jordan, UT 84081\",\n    \"date_sold\": \"Dec 18, 2022\"\n}",
  "{\n    \"address\": \"6043 W Sparrow View Dr, South Jordan, UT 84009\",\n    \"date_sold\": \"Dec 18, 2022\"\n}",
  "{\n    \"address\": \"7622 S New Sycamore Dr # 176, West Jordan, UT 84081\",\n    \"date_sold\": \"Dec 17, 2022\"\n}",
  "{\n    \"address\": \"1221 W Tamarack Rd, Taylorsville, UT 84123\",\n    \"date_sold\": \"Dec 17, 2022\"\n}",
  "{\n    \"address\": \"5094 S Lambeth St, Taylorsville, UT 84129\",\n    \"date_sold\": \"Dec 15, 2022\"\n}",
  "{\n    \"address\": \"13271 S Sky Ranch Rd, Herriman, UT 84096\",\n    \"date_sold\": \"Dec 15, 2022\"\n}",
  "{\n    \"address\": \"6022 W Folly Island Way # 327, South Jordan, UT 84009\",\n    \"date_sold\": \"Dec 15, 2022\"\n}",
  "{\n    \"address\": \"1469 W California Ave, Salt Lake City, UT 84104\",\n    \"date_sold\": \"Dec 14, 2022\"\n}",
  "{\n    \"address\": \"903 E Lafayette St, Sandy, UT 84094\",\n    \"date_sold\": \"Dec 14, 2022\"\n}",
  "{\n    \"address\": \"5909 W Feldspar Way, West Jordan, UT 84081\",\n    \"date_sold\": \"Dec 14, 2022\"\n}",
  "{\n    \"address\": \"9816 S Kramer Dr, Sandy, UT 84092\",\n    \"date_sold\": \"Dec 14, 2022\"\n}",
  "{\n    \"address\": \"5055 W 3000 S, West Valley City, UT 84120\",\n    \"date_sold\": \"Dec 13, 2022\"\n}",
  "{\n    \"address\": \"6642 W Skip Rock Rd # 433, South Jordan, UT 84009\",\n    \"date_sold\": \"Dec 13, 2022\"\n}",
  "{\n    \"address\": \"3743 W Lilac Heights Dr, South Jordan, UT 84095\",\n    \"date_sold\": \"Dec 13, 2022\"\n}",
  "{\n    \"address\": \"2851 W Teamsters Dr, South Jordan, UT 84095\",\n    \"date_sold\": \"Dec 13, 2022\"\n}",
  "{\n    \"address\": \"10224 S Willamette Way, South Jordan, UT 84009\",\n    \"date_sold\": \"Dec 13, 2022\"\n}",
  "{\n    \"address\": \"650 E 4025 S Unit C, Salt Lake City, UT 84107\",\n    \"date_sold\": \"Dec 13, 2022\"\n}",
  "{\n    \"address\": \"824 E 3950 S Apt C, Salt Lake City, UT 84107\",\n    \"date_sold\": \"Dec 12, 2022\"\n}",
  "{\n    \"address\": \"6475 S 1655 E, Salt Lake City, UT 84121\",\n    \"date_sold\": \"Dec 12, 2022\"\n}",
  "{\n    \"address\": \"2417 W Rustic Roads Dr, South Jordan, UT 84095\",\n    \"date_sold\": \"Dec 12, 2022\"\n}",
  "{\n    \"address\": \"4788 W Harbor St, West Valley City, UT 84120\",\n    \"date_sold\": \"Dec 12, 2022\"\n}",
  "{\n    \"address\": \"2476 E Cardinal Way, Salt Lake City, UT 84121\",\n    \"date_sold\": \"Dec 12, 2022\"\n}",
  "{\n    \"address\": \"2220 E Murray Holladay Rd Apt 160, Salt Lake City, UT 84117\",\n    \"date_sold\": \"Dec 12, 2022\"\n}",
  "{\n    \"address\": \"15023 S Pastoral Way, Bluffdale, UT 84065\",\n    \"date_sold\": \"Dec 12, 2022\"\n}",
  "{\n    \"address\": \"5109 W 5320 S, Salt Lake City, UT 84118\",\n    \"date_sold\": \"Dec 12, 2022\"\n}",
  "{\n    \"address\": \"181 E 5460 S Apt 1, Salt Lake City, UT 84107\",\n    \"date_sold\": \"Dec 12, 2022\"\n}",
  "{\n    \"address\": \"4931 W 6400 S, West Jordan, UT 84081\",\n    \"date_sold\": \"Dec 12, 2022\"\n}",
  "{\n    \"address\": \"310 E Carole Cir, Salt Lake City, UT 84115\",\n    \"date_sold\": \"Dec 12, 2022\"\n}",
  "{\n    \"address\": \"1549 E Waterbury Dr Unit L, Salt Lake City, UT 84121\",\n    \"date_sold\": \"Dec 12, 2022\"\n}",
  "{\n    \"address\": \"8969 S Flatiron Dr, Sandy, UT 84093\",\n    \"date_sold\": \"Dec 12, 2022\"\n}",
  "{\n    \"address\": \"116 E Resaca Dr Unit F2, Sandy, UT 84070\",\n    \"date_sold\": \"Dec 11, 2022\"\n}",
  "{\n    \"address\": \"10822 S Wynview Ln, South Jordan, UT 84095\",\n    \"date_sold\": \"Dec 10, 2022\"\n}",
  "{\n    \"address\": \"2191 E Mabey Dr, Salt Lake City, UT 84109\",\n    \"date_sold\": \"Dec 10, 2022\"\n}",
  "{\n    \"address\": \"11632 S Scare Crow Ct, South Jordan, UT 84009\",\n    \"date_sold\": \"Dec 10, 2022\"\n}",
  "{\n    \"address\": \"3897 W Fawn Hill Ln, Bluffdale, UT 84065\",\n    \"date_sold\": \"Dec 10, 2022\"\n}",
  "{\n    \"address\": \"11097 S Willow Walk Dr, South Jordan, UT 84009\",\n    \"date_sold\": \"Dec 27, 2022\"\n}",
  "{\n    \"address\": \"761 W Blue Magic Ln Unit 203, Midvale, UT 84047\",\n    \"date_sold\": \"Dec 27, 2022\"\n}",
  "{\n    \"address\": \"12077 E Milona Dr, Draper, UT 84020\",\n    \"date_sold\": \"Dec 22, 2022\"\n}",
  "{\n    \"address\": \"3524 S Blair Cir, South Salt Lake, UT 84115\",\n    \"date_sold\": \"Dec 20, 2022\"\n}",
  "{\n    \"address\": \"1745 W 400 N, Salt Lake City, UT 84116\",\n    \"date_sold\": \"Dec 19, 2022\"\n}",
  "{\n    \"address\": \"7606 S New Sycamore Dr # 170, West Jordan, UT 84081\",\n    \"date_sold\": \"Dec 18, 2022\"\n}",
  "{\n    \"address\": \"7608 S New Sycamore Dr # 169, West Jordan, UT 84081\",\n    \"date_sold\": \"Dec 18, 2022\"\n}",
  "{\n    \"address\": \"7602 S New Sycamore Dr # 172, West Jordan, UT 84081\",\n    \"date_sold\": \"Dec 18, 2022\"\n}",
  "{\n    \"address\": \"6043 W Sparrow View Dr, South Jordan, UT 84009\",\n    \"date_sold\": \"Dec 18, 2022\"\n}",
  "{\n    \"address\": \"7622 S New Sycamore Dr # 176, West Jordan, UT 84081\",\n    \"date_sold\": \"Dec 17, 2022\"\n}",
  "{\n    \"address\": \"1221 W Tamarack Rd, Taylorsville, UT 84123\",\n    \"date_sold\": \"Dec 17, 2022\"\n}",
  "{\n    \"address\": \"5094 S Lambeth St, Taylorsville, UT 84129\",\n    \"date_sold\": \"Dec 15, 2022\"\n}",
  "{\n    \"address\": \"6022 W Folly Island Way # 327, South Jordan, UT 84009\",\n    \"date_sold\": \"Dec 15, 2022\"\n}",
  "{\n    \"address\": \"13271 S Sky Ranch Rd, Herriman, UT 84096\",\n    \"date_sold\": \"Dec 15, 2022\"\n}",
  "{\n    \"address\": \"1469 W California Ave, Salt Lake City, UT 84104\",\n    \"date_sold\": \"Dec 14, 2022\"\n}",
  "{\n    \"address\": \"903 E Lafayette St, Sandy, UT 84094\",\n    \"date_sold\": \"Dec 14, 2022\"\n}",
  "{\n    \"address\": \"5909 W Feldspar Way, West Jordan, UT 84081\",\n    \"date_sold\": \"Dec 14, 2022\"\n}",
  "{\n    \"address\": \"9816 S Kramer Dr, Sandy, UT 84092\",\n    \"date_sold\": \"Dec 14, 2022\"\n}",
  "{\n    \"address\": \"5055 W 3000 S, West Valley City, UT 84120\",\n    \"date_sold\": \"Dec 13, 2022\"\n}",
  "{\n    \"address\": \"6642 W Skip Rock Rd # 433, South Jordan, UT 84009\",\n    \"date_sold\": \"Dec 13, 2022\"\n}",
  "{\n    \"address\": \"3743 W Lilac Heights Dr, South Jordan, UT 84095\",\n    \"date_sold\": \"Dec 13, 2022\"\n}",
  "{\n    \"address\": \"2851 W Teamsters Dr, South Jordan, UT 84095\",\n    \"date_sold\": \"Dec 13, 2022\"\n}",
  "{\n    \"address\": \"10224 S Willamette Way, South Jordan, UT 84009\",\n    \"date_sold\": \"Dec 13, 2022\"\n}",
  "{\n    \"address\": \"650 E 4025 S Unit C, Salt Lake City, UT 84107\",\n    \"date_sold\": \"Dec 13, 2022\"\n}",
  "{\n    \"address\": \"824 E 3950 S Apt C, Salt Lake City, UT 84107\",\n    \"date_sold\": \"Dec 12, 2022\"\n}",
  "{\n    \"address\": \"6475 S 1655 E, Salt Lake City, UT 84121\",\n    \"date_sold\": \"Dec 12, 2022\"\n}",
  "{\n    \"address\": \"2417 W Rustic Roads Dr, South Jordan, UT 84095\",\n    \"date_sold\": \"Dec 12, 2022\"\n}",
  "{\n    \"address\": \"4788 W Harbor St, West Valley City, UT 84120\",\n    \"date_sold\": \"Dec 12, 2022\"\n}",
  "{\n    \"address\": \"2476 E Cardinal Way, Salt Lake City, UT 84121\",\n    \"date_sold\": \"Dec 12, 2022\"\n}",
  "{\n    \"address\": \"2220 E Murray Holladay Rd Apt 160, Salt Lake City, UT 84117\",\n    \"date_sold\": \"Dec 12, 2022\"\n}",
  "{\n    \"address\": \"15023 S Pastoral Way, Bluffdale, UT 84065\",\n    \"date_sold\": \"Dec 12, 2022\"\n}",
  "{\n    \"address\": \"5109 W 5320 S, Salt Lake City, UT 84118\",\n    \"date_sold\": \"Dec 12, 2022\"\n}",
  "{\n    \"address\": \"181 E 5460 S Apt 1, Salt Lake City, UT 84107\",\n    \"date_sold\": \"Dec 12, 2022\"\n}",
  "{\n    \"address\": \"4931 W 6400 S, West Jordan, UT 84081\",\n    \"date_sold\": \"Dec 12, 2022\"\n}",
  "{\n    \"address\": \"310 E Carole Cir, Salt Lake City, UT 84115\",\n    \"date_sold\": \"Dec 12, 2022\"\n}",
  "{\n    \"address\": \"8969 S Flatiron Dr, Sandy, UT 84093\",\n    \"date_sold\": \"Dec 12, 2022\"\n}",
  "{\n    \"address\": \"1549 E Waterbury Dr Unit L, Salt Lake City, UT 84121\",\n    \"date_sold\": \"Dec 12, 2022\"\n}",
  "{\n    \"address\": \"116 E Resaca Dr Unit F2, Sandy, UT 84070\",\n    \"date_sold\": \"Dec 11, 2022\"\n}",
  "{\n    \"address\": \"10822 S Wynview Ln, South Jordan, UT 84095\",\n    \"date_sold\": \"Dec 10, 2022\"\n}",
  "{\n    \"address\": \"2191 E Mabey Dr, Salt Lake City, UT 84109\",\n    \"date_sold\": \"Dec 10, 2022\"\n}",
  "{\n    \"address\": \"11632 S Scare Crow Ct, South Jordan, UT 84009\",\n    \"date_sold\": \"Dec 10, 2022\"\n}",
  "{\n    \"address\": \"3897 W Fawn Hill Ln, Bluffdale, UT 84065\",\n    \"date_sold\": \"Dec 10, 2022\"\n}",
  "{\n    \"address\": \"11097 S Willow Walk Dr, South Jordan, UT 84009\",\n    \"date_sold\": \"Dec 27, 2022\"\n}",
  "{\n    \"address\": \"761 W Blue Magic Ln Unit 203, Midvale, UT 84047\",\n    \"date_sold\": \"Dec 27, 2022\"\n}",
  "{\n    \"address\": \"12077 E Milona Dr, Draper, UT 84020\",\n    \"date_sold\": \"Dec 22, 2022\"\n}",
  "{\n    \"address\": \"3524 S Blair Cir, South Salt Lake, UT 84115\",\n    \"date_sold\": \"Dec 20, 2022\"\n}",
  "{\n    \"address\": \"1745 W 400 N, Salt Lake City, UT 84116\",\n    \"date_sold\": \"Dec 19, 2022\"\n}",
  "{\n    \"address\": \"7606 S New Sycamore Dr # 170, West Jordan, UT 84081\",\n    \"date_sold\": \"Dec 18, 2022\"\n}",
  "{\n    \"address\": \"7608 S New Sycamore Dr # 169, West Jordan, UT 84081\",\n    \"date_sold\": \"Dec 18, 2022\"\n}",
  "{\n    \"address\": \"7602 S New Sycamore Dr # 172, West Jordan, UT 84081\",\n    \"date_sold\": \"Dec 18, 2022\"\n}",
  "{\n    \"address\": \"6043 W Sparrow View Dr, South Jordan, UT 84009\",\n    \"date_sold\": \"Dec 18, 2022\"\n}",
  "{\n    \"address\": \"7622 S New Sycamore Dr # 176, West Jordan, UT 84081\",\n    \"date_sold\": \"Dec 17, 2022\"\n}",
  "{\n    \"address\": \"1221 W Tamarack Rd, Taylorsville, UT 84123\",\n    \"date_sold\": \"Dec 17, 2022\"\n}",
  "{\n    \"address\": \"5094 S Lambeth St, Taylorsville, UT 84129\",\n    \"date_sold\": \"Dec 15, 2022\"\n}",
  "{\n    \"address\": \"6022 W Folly Island Way # 327, South Jordan, UT 84009\",\n    \"date_sold\": \"Dec 15, 2022\"\n}",
  "{\n    \"address\": \"13271 S Sky Ranch Rd, Herriman, UT 84096\",\n    \"date_sold\": \"Dec 15, 2022\"\n}",
  "{\n    \"address\": \"1469 W California Ave, Salt Lake City, UT 84104\",\n    \"date_sold\": \"Dec 14, 2022\"\n}",
  "{\n    \"address\": \"903 E Lafayette St, Sandy, UT 84094\",\n    \"date_sold\": \"Dec 14, 2022\"\n}",
  "{\n    \"address\": \"5909 W Feldspar Way, West Jordan, UT 84081\",\n    \"date_sold\": \"Dec 14, 2022\"\n}",
  "{\n    \"address\": \"9816 S Kramer Dr, Sandy, UT 84092\",\n    \"date_sold\": \"Dec 14, 2022\"\n}",
  "{\n    \"address\": \"5055 W 3000 S, West Valley City, UT 84120\",\n    \"date_sold\": \"Dec 13, 2022\"\n}",
  "{\n    \"address\": \"6642 W Skip Rock Rd # 433, South Jordan, UT 84009\",\n    \"date_sold\": \"Dec 13, 2022\"\n}",
  "{\n    \"address\": \"3743 W Lilac Heights Dr, South Jordan, UT 84095\",\n    \"date_sold\": \"Dec 13, 2022\"\n}",
  "{\n    \"address\": \"2851 W Teamsters Dr, South Jordan, UT 84095\",\n    \"date_sold\": \"Dec 13, 2022\"\n}",
  "{\n    \"address\": \"10224 S Willamette Way, South Jordan, UT 84009\",\n    \"date_sold\": \"Dec 13, 2022\"\n}",
  "{\n    \"address\": \"650 E 4025 S Unit C, Salt Lake City, UT 84107\",\n    \"date_sold\": \"Dec 13, 2022\"\n}",
  "{\n    \"address\": \"824 E 3950 S Apt C, Salt Lake City, UT 84107\",\n    \"date_sold\": \"Dec 12, 2022\"\n}",
  "{\n    \"address\": \"6475 S 1655 E, Salt Lake City, UT 84121\",\n    \"date_sold\": \"Dec 12, 2022\"\n}",
  "{\n    \"address\": \"2417 W Rustic Roads Dr, South Jordan, UT 84095\",\n    \"date_sold\": \"Dec 12, 2022\"\n}",
  "{\n    \"address\": \"4788 W Harbor St, West Valley City, UT 84120\",\n    \"date_sold\": \"Dec 12, 2022\"\n}",
  "{\n    \"address\": \"2476 E Cardinal Way, Salt Lake City, UT 84121\",\n    \"date_sold\": \"Dec 12, 2022\"\n}",
  "{\n    \"address\": \"2220 E Murray Holladay Rd Apt 160, Salt Lake City, UT 84117\",\n    \"date_sold\": \"Dec 12, 2022\"\n}",
  "{\n    \"address\": \"15023 S Pastoral Way, Bluffdale, UT 84065\",\n    \"date_sold\": \"Dec 12, 2022\"\n}",
  "{\n    \"address\": \"5109 W 5320 S, Salt Lake City, UT 84118\",\n    \"date_sold\": \"Dec 12, 2022\"\n}",
  "{\n    \"address\": \"181 E 5460 S Apt 1, Salt Lake City, UT 84107\",\n    \"date_sold\": \"Dec 12, 2022\"\n}",
  "{\n    \"address\": \"4931 W 6400 S, West Jordan, UT 84081\",\n    \"date_sold\": \"Dec 12, 2022\"\n}",
  "{\n    \"address\": \"310 E Carole Cir, Salt Lake City, UT 84115\",\n    \"date_sold\": \"Dec 12, 2022\"\n}",
  "{\n    \"address\": \"8969 S Flatiron Dr, Sandy, UT 84093\",\n    \"date_sold\": \"Dec 12, 2022\"\n}",
  "{\n    \"address\": \"1549 E Waterbury Dr Unit L, Salt Lake City, UT 84121\",\n    \"date_sold\": \"Dec 12, 2022\"\n}",
  "{\n    \"address\": \"116 E Resaca Dr Unit F2, Sandy, UT 84070\",\n    \"date_sold\": \"Dec 11, 2022\"\n}",
  "{\n    \"address\": \"10822 S Wynview Ln, South Jordan, UT 84095\",\n    \"date_sold\": \"Dec 10, 2022\"\n}",
  "{\n    \"address\": \"2191 E Mabey Dr, Salt Lake City, UT 84109\",\n    \"date_sold\": \"Dec 10, 2022\"\n}",
  "{\n    \"address\": \"11632 S Scare Crow Ct, South Jordan, UT 84009\",\n    \"date_sold\": \"Dec 10, 2022\"\n}",
  "{\n    \"address\": \"3897 W Fawn Hill Ln, Bluffdale, UT 84065\",\n    \"date_sold\": \"Dec 10, 2022\"\n}",
  "{\n    \"address\": \"11097 S Willow Walk Dr, South Jordan, UT 84009\",\n    \"date_sold\": \"Dec 27, 2022\"\n}",
  "{\n    \"address\": \"761 W Blue Magic Ln Unit 203, Midvale, UT 84047\",\n    \"date_sold\": \"Dec 27, 2022\"\n}",
  "{\n    \"address\": \"12077 E Milona Dr, Draper, UT 84020\",\n    \"date_sold\": \"Dec 22, 2022\"\n}",
  "{\n    \"address\": \"3524 S Blair Cir, South Salt Lake, UT 84115\",\n    \"date_sold\": \"Dec 20, 2022\"\n}",
  "{\n    \"address\": \"1745 W 400 N, Salt Lake City, UT 84116\",\n    \"date_sold\": \"Dec 19, 2022\"\n}",
  "{\n    \"address\": \"7606 S New Sycamore Dr # 170, West Jordan, UT 84081\",\n    \"date_sold\": \"Dec 18, 2022\"\n}",
  "{\n    \"address\": \"7608 S New Sycamore Dr # 169, West Jordan, UT 84081\",\n    \"date_sold\": \"Dec 18, 2022\"\n}",
  "{\n    \"address\": \"7602 S New Sycamore Dr # 172, West Jordan, UT 84081\",\n    \"date_sold\": \"Dec 18, 2022\"\n}",
  "{\n    \"address\": \"6043 W Sparrow View Dr, South Jordan, UT 84009\",\n    \"date_sold\": \"Dec 18, 2022\"\n}",
  "{\n    \"address\": \"7622 S New Sycamore Dr # 176, West Jordan, UT 84081\",\n    \"date_sold\": \"Dec 17, 2022\"\n}",
  "{\n    \"address\": \"1221 W Tamarack Rd, Taylorsville, UT 84123\",\n    \"date_sold\": \"Dec 17, 2022\"\n}",
  "{\n    \"address\": \"5094 S Lambeth St, Taylorsville, UT 84129\",\n    \"date_sold\": \"Dec 15, 2022\"\n}",
  "{\n    \"address\": \"6022 W Folly Island Way # 327, South Jordan, UT 84009\",\n    \"date_sold\": \"Dec 15, 2022\"\n}",
  "{\n    \"address\": \"13271 S Sky Ranch Rd, Herriman, UT 84096\",\n    \"date_sold\": \"Dec 15, 2022\"\n}",
  "{\n    \"address\": \"903 E Lafayette St, Sandy, UT 84094\",\n    \"date_sold\": \"Dec 14, 2022\"\n}",
  "{\n    \"address\": \"1469 W California Ave, Salt Lake City, UT 84104\",\n    \"date_sold\": \"Dec 14, 2022\"\n}",
  "{\n    \"address\": \"5909 W Feldspar Way, West Jordan, UT 84081\",\n    \"date_sold\": \"Dec 14, 2022\"\n}",
  "{\n    \"address\": \"9816 S Kramer Dr, Sandy, UT 84092\",\n    \"date_sold\": \"Dec 14, 2022\"\n}",
  "{\n    \"address\": \"5055 W 3000 S, West Valley City, UT 84120\",\n    \"date_sold\": \"Dec 13, 2022\"\n}",
  "{\n    \"address\": \"6642 W Skip Rock Rd # 433, South Jordan, UT 84009\",\n    \"date_sold\": \"Dec 13, 2022\"\n}",
  "{\n    \"address\": \"3743 W Lilac Heights Dr, South Jordan, UT 84095\",\n    \"date_sold\": \"Dec 13, 2022\"\n}",
  "{\n    \"address\": \"2851 W Teamsters Dr, South Jordan, UT 84095\",\n    \"date_sold\": \"Dec 13, 2022\"\n}",
  "{\n    \"address\": \"10224 S Willamette Way, South Jordan, UT 84009\",\n    \"date_sold\": \"Dec 13, 2022\"\n}",
  "{\n    \"address\": \"650 E 4025 S Unit C, Salt Lake City, UT 84107\",\n    \"date_sold\": \"Dec 13, 2022\"\n}",
  "{\n    \"address\": \"824 E 3950 S Apt C, Salt Lake City, UT 84107\",\n    \"date_sold\": \"Dec 12, 2022\"\n}",
  "{\n    \"address\": \"2417 W Rustic Roads Dr, South Jordan, UT 84095\",\n    \"date_sold\": \"Dec 12, 2022\"\n}",
  "{\n    \"address\": \"6475 S 1655 E, Salt Lake City, UT 84121\",\n    \"date_sold\": \"Dec 12, 2022\"\n}",
  "{\n    \"address\": \"4788 W Harbor St, West Valley City, UT 84120\",\n    \"date_sold\": \"Dec 12, 2022\"\n}",
  "{\n    \"address\": \"2476 E Cardinal Way, Salt Lake City, UT 84121\",\n    \"date_sold\": \"Dec 12, 2022\"\n}",
  "{\n    \"address\": \"5109 W 5320 S, Salt Lake City, UT 84118\",\n    \"date_sold\": \"Dec 12, 2022\"\n}",
  "{\n    \"address\": \"15023 S Pastoral Way, Bluffdale, UT 84065\",\n    \"date_sold\": \"Dec 12, 2022\"\n}",
  "{\n    \"address\": \"2220 E Murray Holladay Rd Apt 160, Salt Lake City, UT 84117\",\n    \"date_sold\": \"Dec 12, 2022\"\n}",
  "{\n    \"address\": \"181 E 5460 S Apt 1, Salt Lake City, UT 84107\",\n    \"date_sold\": \"Dec 12, 2022\"\n}",
  "{\n    \"address\": \"4931 W 6400 S, West Jordan, UT 84081\",\n    \"date_sold\": \"Dec 12, 2022\"\n}",
  "{\n    \"address\": \"310 E Carole Cir, Salt Lake City, UT 84115\",\n    \"date_sold\": \"Dec 12, 2022\"\n}",
  "{\n    \"address\": \"8969 S Flatiron Dr, Sandy, UT 84093\",\n    \"date_sold\": \"Dec 12, 2022\"\n}",
  "{\n    \"address\": \"1549 E Waterbury Dr Unit L, Salt Lake City, UT 84121\",\n    \"date_sold\": \"Dec 12, 2022\"\n}",
  "{\n    \"address\": \"116 E Resaca Dr Unit F2, Sandy, UT 84070\",\n    \"date_sold\": \"Dec 11, 2022\"\n}",
  "{\n    \"address\": \"2191 E Mabey Dr, Salt Lake City, UT 84109\",\n    \"date_sold\": \"Dec 10, 2022\"\n}",
  "{\n    \"address\": \"10822 S Wynview Ln, South Jordan, UT 84095\",\n    \"date_sold\": \"Dec 10, 2022\"\n}",
  "{\n    \"address\": \"11632 S Scare Crow Ct, South Jordan, UT 84009\",\n    \"date_sold\": \"Dec 10, 2022\"\n}",
  "{\n    \"address\": \"3897 W Fawn Hill Ln, Bluffdale, UT 84065\",\n    \"date_sold\": \"Dec 10, 2022\"\n}",
  "{\n    \"address\": \"11097 S Willow Walk Dr, South Jordan, UT 84009\",\n    \"date_sold\": \"Dec 27, 2022\"\n}",
  "{\n    \"address\": \"761 W Blue Magic Ln Unit 203, Midvale, UT 84047\",\n    \"date_sold\": \"Dec 27, 2022\"\n}",
  "{\n    \"address\": \"12077 E Milona Dr, Draper, UT 84020\",\n    \"date_sold\": \"Dec 22, 2022\"\n}",
  "{\n    \"address\": \"3524 S Blair Cir, South Salt Lake, UT 84115\",\n    \"date_sold\": \"Dec 20, 2022\"\n}",
  "{\n    \"address\": \"1745 W 400 N, Salt Lake City, UT 84116\",\n    \"date_sold\": \"Dec 19, 2022\"\n}",
  "{\n    \"address\": \"7606 S New Sycamore Dr # 170, West Jordan, UT 84081\",\n    \"date_sold\": \"Dec 18, 2022\"\n}",
  "{\n    \"address\": \"7608 S New Sycamore Dr # 169, West Jordan, UT 84081\",\n    \"date_sold\": \"Dec 18, 2022\"\n}",
  "{\n    \"address\": \"7602 S New Sycamore Dr # 172, West Jordan, UT 84081\",\n    \"date_sold\": \"Dec 18, 2022\"\n}",
  "{\n    \"address\": \"6043 W Sparrow View Dr, South Jordan, UT 84009\",\n    \"date_sold\": \"Dec 18, 2022\"\n}",
  "{\n    \"address\": \"7622 S New Sycamore Dr # 176, West Jordan, UT 84081\",\n    \"date_sold\": \"Dec 17, 2022\"\n}",
  "{\n    \"address\": \"1221 W Tamarack Rd, Taylorsville, UT 84123\",\n    \"date_sold\": \"Dec 17, 2022\"\n}",
  "{\n    \"address\": \"5094 S Lambeth St, Taylorsville, UT 84129\",\n    \"date_sold\": \"Dec 15, 2022\"\n}",
  "{\n    \"address\": \"13271 S Sky Ranch Rd, Herriman, UT 84096\",\n    \"date_sold\": \"Dec 15, 2022\"\n}",
  "{\n    \"address\": \"6022 W Folly Island Way # 327, South Jordan, UT 84009\",\n    \"date_sold\": \"Dec 15, 2022\"\n}",
  "{\n    \"address\": \"903 E Lafayette St, Sandy, UT 84094\",\n    \"date_sold\": \"Dec 14, 2022\"\n}",
  "{\n    \"address\": \"1469 W California Ave, Salt Lake City, UT 84104\",\n    \"date_sold\": \"Dec 14, 2022\"\n}",
  "{\n    \"address\": \"5909 W Feldspar Way, West Jordan, UT 84081\",\n    \"date_sold\": \"Dec 14, 2022\"\n}",
  "{\n    \"address\": \"9816 S Kramer Dr, Sandy, UT 84092\",\n    \"date_sold\": \"Dec 14, 2022\"\n}",
  "{\n    \"address\": \"5055 W 3000 S, West Valley City, UT 84120\",\n    \"date_sold\": \"Dec 13, 2022\"\n}",
  "{\n    \"address\": \"6642 W Skip Rock Rd # 433, South Jordan, UT 84009\",\n    \"date_sold\": \"Dec 13, 2022\"\n}",
  "{\n    \"address\": \"3743 W Lilac Heights Dr, South Jordan, UT 84095\",\n    \"date_sold\": \"Dec 13, 2022\"\n}",
  "{\n    \"address\": \"2851 W Teamsters Dr, South Jordan, UT 84095\",\n    \"date_sold\": \"Dec 13, 2022\"\n}",
  "{\n    \"address\": \"10224 S Willamette Way, South Jordan, UT 84009\",\n    \"date_sold\": \"Dec 13, 2022\"\n}",
  "{\n    \"address\": \"650 E 4025 S Unit C, Salt Lake City, UT 84107\",\n    \"date_sold\": \"Dec 13, 2022\"\n}",
  "{\n    \"address\": \"824 E 3950 S Apt C, Salt Lake City, UT 84107\",\n    \"date_sold\": \"Dec 12, 2022\"\n}",
  "{\n    \"address\": \"2417 W Rustic Roads Dr, South Jordan, UT 84095\",\n    \"date_sold\": \"Dec 12, 2022\"\n}",
  "{\n    \"address\": \"6475 S 1655 E, Salt Lake City, UT 84121\",\n    \"date_sold\": \"Dec 12, 2022\"\n}",
  "{\n    \"address\": \"4788 W Harbor St, West Valley City, UT 84120\",\n    \"date_sold\": \"Dec 12, 2022\"\n}",
  "{\n    \"address\": \"2476 E Cardinal Way, Salt Lake City, UT 84121\",\n    \"date_sold\": \"Dec 12, 2022\"\n}",
  "{\n    \"address\": \"5109 W 5320 S, Salt Lake City, UT 84118\",\n    \"date_sold\": \"Dec 12, 2022\"\n}",
  "{\n    \"address\": \"15023 S Pastoral Way, Bluffdale, UT 84065\",\n    \"date_sold\": \"Dec 12, 2022\"\n}",
  "{\n    \"address\": \"2220 E Murray Holladay Rd Apt 160, Salt Lake City, UT 84117\",\n    \"date_sold\": \"Dec 12, 2022\"\n}",
  "{\n    \"address\": \"181 E 5460 S Apt 1, Salt Lake City, UT 84107\",\n    \"date_sold\": \"Dec 12, 2022\"\n}",
  "{\n    \"address\": \"4931 W 6400 S, West Jordan, UT 84081\",\n    \"date_sold\": \"Dec 12, 2022\"\n}",
  "{\n    \"address\": \"310 E Carole Cir, Salt Lake City, UT 84115\",\n    \"date_sold\": \"Dec 12, 2022\"\n}",
  "{\n    \"address\": \"1549 E Waterbury Dr Unit L, Salt Lake City, UT 84121\",\n    \"date_sold\": \"Dec 12, 2022\"\n}",
  "{\n    \"address\": \"8969 S Flatiron Dr, Sandy, UT 84093\",\n    \"date_sold\": \"Dec 12, 2022\"\n}",
  "{\n    \"address\": \"116 E Resaca Dr Unit F2, Sandy, UT 84070\",\n    \"date_sold\": \"Dec 11, 2022\"\n}",
  "{\n    \"address\": \"2191 E Mabey Dr, Salt Lake City, UT 84109\",\n    \"date_sold\": \"Dec 10, 2022\"\n}",
  "{\n    \"address\": \"10822 S Wynview Ln, South Jordan, UT 84095\",\n    \"date_sold\": \"Dec 10, 2022\"\n}",
  "{\n    \"address\": \"11632 S Scare Crow Ct, South Jordan, UT 84009\",\n    \"date_sold\": \"Dec 10, 2022\"\n}",
  "{\n    \"address\": \"3897 W Fawn Hill Ln, Bluffdale, UT 84065\",\n    \"date_sold\": \"Dec 10, 2022\"\n}"
]
